redditreport/RedditPost.py
redditreport/RedditReport.py
redditreport/RedditUser.py
redditreport/__init__.py
redditreport-0.4.0.dist-info/LICENSE
redditreport-0.4.0.dist-info/METADATA
redditreport-0.4.0.dist-info/WHEEL
redditreport-0.4.0.dist-info/top_level.txt
redditreport-0.4.0.dist-info/RECORD
