Metadata-Version: 2.1
Name: redditreport
Version: 0.4.0
Summary: Tools to create reports using the Reddit API + praw library.
Home-page: https://github.com/FARBEX97/redditreport
Author: FARBEX97
Author-email: fernandoarbexcv@gmail.com
License: UNKNOWN
Platform: UNKNOWN
Classifier: Programming Language :: Python :: 3
Classifier: License :: OSI Approved :: MIT License
Classifier: Operating System :: OS Independent
Requires-Python: >=3.6
